datasaku/__init__.py
datasaku/datasaku_calendar.py
datasaku/datasaku_geo.py
datasaku/datasaku_google.py
datasaku/datasaku_minio.py
datasaku/datasaku_nlp.py
datasaku/datasaku_pandas.py
datasaku/datasaku_presto.py
datasaku/datasaku_s3.py
datasaku/datasaku_snowflake.py
datasaku/datasaku_starburst.py
datasaku/datasaku_viz.py
datasaku-0.0.8.dist-info/LICENSE
datasaku-0.0.8.dist-info/METADATA
datasaku-0.0.8.dist-info/WHEEL
datasaku-0.0.8.dist-info/top_level.txt
datasaku-0.0.8.dist-info/RECORD
