Metadata-Version: 2.1
Name: datasaku
Version: 0.0.8
Summary: A small example package
Author-email: kurangdoa <rando.bayor@gmail.com>
License: Copyright (c) 2022 The Python Packaging Authority
Project-URL: Homepage, https://github.com/pypa/sampleproject
Project-URL: Bug Tracker, https://github.com/pypa/sampleproject/issues
Classifier: Programming Language :: Python :: 3
Classifier: License :: OSI Approved :: MIT License
Classifier: Operating System :: OS Independent
Requires-Python: >=3.7
License-File: LICENSE
Requires-Dist: boto3 (==1.26.47)
Requires-Dist: Fiona (==1.8.22)
Requires-Dist: fuzzywuzzy (==0.18.0)
Requires-Dist: geopandas (==0.12.2)
Requires-Dist: google-api-python-client (==2.72.0)
Requires-Dist: google-auth-oauthlib (==0.8.0)
Requires-Dist: h3 (==3.7.6)
Requires-Dist: importlib-resources (==5.10.2)
Requires-Dist: matplotlib (==3.6.2)
Requires-Dist: minio (==7.1.14)
Requires-Dist: pandas (==1.5.2)
Requires-Dist: plotly (==5.11.0)
Requires-Dist: protobuf (==4.23.0)
Requires-Dist: PyHive (==0.6.5)
Requires-Dist: Requests (==2.30.0)
Requires-Dist: seaborn (==0.12.2)
Requires-Dist: snowflake (==0.0.3)
Requires-Dist: SQLAlchemy (==1.4.46)
Requires-Dist: urllib3 (==1.26.15)
